yopo/__init__.py
yopo/__version__.py
yopo/dashboard.py
yopo/util.py
yopo-0.0.21.dist-info/LICENSE.txt
yopo-0.0.21.dist-info/METADATA
yopo-0.0.21.dist-info/WHEEL
yopo-0.0.21.dist-info/top_level.txt
yopo-0.0.21.dist-info/RECORD
