Metadata-Version: 2.1
Name: yopo
Version: 0.0.21
Summary: You Plot Only Once
Home-page: https://github.com/chekoduadarsh/YOPO-You-Only-Plot-Once
Author: Adarsh Chekodu
Author-email: chekodu.adarsh@gmail.com
License: Apache License 2.0
Platform: UNKNOWN
Classifier: Programming Language :: Python :: 3
Classifier: Operating System :: OS Independent
License-File: LICENSE.txt
Requires-Dist: MarkupSafe (>=2.0)
Requires-Dist: jupyter-dash
Requires-Dist: click (>=7.1.2)
Requires-Dist: ipython
Requires-Dist: jupyter
Requires-Dist: wtforms
Requires-Dist: dash (==2.0.0)
Requires-Dist: dash-daq
Requires-Dist: pandas
Requires-Dist: numpy
Requires-Dist: dash-bootstrap-components
Requires-Dist: pyngrok
